{
  "campaign_id": "뉴턴젤리_20260329_203641",
  "product_name": "뉴턴젤리",
  "created_at": "2026-03-29T21:00:00+09:00",
  "persona": {
    "age_range": "36~48세 엄마",
    "child_age": "만 4~13세",
    "core_concern": "아이가 산만하고 예민해서 ADHD가 의심되지만 진단 기준은 아닌 회색지대. 약 처방 전 자연 성분으로 먼저 시도하고 싶은 욕구가 강함.",
    "tried_before": "오메가3, 유산균, 마그네슘, 소아과·한의원 상담, 행동 교정 시도",
    "info_channels": "맘카페(맘스홀릭, 레몬테라스), 인스타그램 육아 계정, 카카오톡 오픈채팅, 쿠팡·네이버 리뷰",
    "trigger_keywords": ["산만한 아이", "ADHD 걱정", "예민한 기질", "감정 폭발", "선생님 전화", "집중력 부족", "약 말고 자연적인 방법"]
  },
  "campaign_keywords": {
    "trigger": ["산만함", "ADHD", "예민함", "집중력", "선생님 전화", "감정 폭발", "수업 중 돌아다님"],
    "ingredient": ["테아닌", "트립토판", "가바", "세로토닌", "천연 성분"],
    "benefit": ["기질 개선", "차분함", "집중력 향상", "감정 안정", "뇌 균형", "스트레스 감소", "악순환 차단"]
  },
  "image_briefs": [],
  "video_briefs": [
    {
      "brief_id": "vid_1",
      "format": "video",
      "duration_sec": 30,
      "outline_type": "A형",
      "appearance_type": "사람등장형",
      "narration": "여성VO_따뜻한",
      "concept_title": "선생님 전화가 줄었어요",
      "angle": "페인포인트",
      "reframe_type": "문제재정의",
      "core_message": "아이의 산만함은 의지 문제가 아니라 스트레스로 인한 뇌 신경전달물질 불균형이 원인이며, 테아닌·트립토판·가바가 이 불균형을 바로잡아 줍니다.",
      "head": "엄마가 핸드폰 화면을 보며 한숨 쉬는 클로즈업. 화면에 '담임선생님' 부재중 전화 알림. 자막: '오늘 또 선생님한테 전화 왔어요...' (3초)",
      "body": "[씬1] 학교에서 수업 중 자리 이탈하는 아이 짧은 컷 (3초). [씬2] 자막+VO: '산만한 건 의지 문제가 아닐 수 있어요. 스트레스 → 코르티솔 과다 → 세로토닌·도파민 불균형. 이 악순환이 원인입니다.' 뇌 신경전달물질 밸런스 간단 인포그래픽 오버레이 (8초). [씬3] 테아닌 150mg + 트립토판 150mg + 가바 성분 텍스트 등장, 제품 패키지 클로즈업 (5초). [씬4] 같은 아이가 차분하게 책상에 앉아 공부하는 장면. 엄마가 뒤에서 미소 짓는 라이프스타일 컷 (5초).",
      "legs": "자막+VO: '14일 안에 변화 없으면 전액 환불. 뉴턴젤리, 지금 시작하세요.' 제품 패키지 + 100% 환불 배지 + CTA 버튼 (3초)",
      "narrative_arc": "도입(선생님 전화라는 공포 상황으로 즉각 공감) → 전개(산만함의 과학적 원인을 재정의하고 성분으로 해결책 제시) → 결말(변화된 아이 모습 + 환불 보장으로 리스크 제거)",
      "visual_direction": "도입은 어두운 실내 조명에서 엄마 표정 클로즈업으로 무거운 분위기. 중반 인포그래픽은 딥그린(#397900) 배경에 오렌지(#FF7043) 강조 텍스트. 후반은 자연광 가득한 밝은 거실로 전환하며 희망적 톤. 전체적으로 무거움에서 밝음으로 감정 곡선 설계.",
      "target_emotion": "불안해소",
      "key_copy_direction": "엄마의 실제 일상 언어로 시작해 과학적 근거로 전환. '의지 문제가 아니다'라는 재정의가 핵심. VO는 친구 엄마가 조언해주는 것처럼 따뜻하게.",
      "keywords": ["선생님 전화", "산만함", "뇌 불균형", "테아닌", "악순환"],
      "watch_reasons": ["몰입포맷", "실용이익"],
      "buy_reasons": ["신뢰", "개선확신"],
      "compliance_notes": "ADHD 치료를 암시하는 표현 금지. '뇌 불균형'은 일반적 영양 균형 맥락에서만 사용. 선생님 전화 장면은 특정 학교·교사를 연상시키지 않도록 일반화. '전액 환불'은 조건(10포 이하, 14일 이내) 소자막으로 표기."
    },
    {
      "brief_id": "vid_2",
      "format": "video",
      "duration_sec": 15,
      "outline_type": "E형",
      "appearance_type": "모션그래픽형",
      "narration": "텍스트자막전용",
      "concept_title": "오메가3만으로 충분하다고요?",
      "angle": "비교형",
      "reframe_type": "경쟁비교",
      "core_message": "오메가3만으로는 산만함의 근본 원인인 신경전달물질 불균형을 해결할 수 없으며, 테아닌·트립토판·가바의 황금 조합이 필요합니다.",
      "head": "화면 중앙에 큰 텍스트: '오메가3 먹이고 있는데 여전히 산만하다면?' 텍스트가 흔들리듯 등장. BGM은 긴장감 있는 짧은 비트. (2초)",
      "body": "[씬1] 좌측에 오메가3 아이콘, 화살표로 'DHA → 뇌세포 막 구성'만 연결. 자막: '오메가3는 뇌세포 영양소. 하지만 산만함의 원인은 신경전달물질 불균형.' (4초). [씬2] 우측에 테아닌·트립토판·가바 3가지 아이콘이 차례로 등장. 각각 '스트레스 완화', '세로토닌 생성', '신경 안정' 연결선. 자막: '산만함엔 기질 성분 황금 조합이 필요합니다.' (5초). [씬3] 뉴턴젤리 제품 모션 등장. '200만개 판매 돌파' 배지 팝업. (2초)",
      "legs": "자막: '지금 35,000원 쿠폰팩 받고 시작하기' + CTA 버튼 애니메이션. (2초)",
      "narrative_arc": "도입(기존 해결책의 한계를 역발상으로 질문) → 전개(오메가3 vs 기질 성분의 작용 영역 차이를 시각적으로 대비) → 결말(제품 제시 + 쿠폰 혜택 CTA)",
      "visual_direction": "전체 모션그래픽. 딥그린(#397900) 배경 위 화이트 텍스트, 강조 키워드는 오렌지(#FF7043). 오메가3 영역은 회색 톤으로 한정적으로 표현, 기질 성분 영역은 딥그린+옐로우(#FFF9C4)로 풍성하게 표현. 인포그래픽 다이어그램 스타일.",
      "target_emotion": "신뢰",
      "key_copy_direction": "기존에 먹이던 오메가3의 한계를 지적하되 부정하지 않고, 보완적 관점에서 기질 성분의 필요성을 논리적으로 설명. 짧고 임팩트 있는 자막 위주. 무음 환경에서도 완전히 이해 가능하도록 설계.",
      "keywords": ["오메가3", "기질 성분", "황금 조합", "뇌 불균형", "트립토판"],
      "watch_reasons": ["의외성", "시각차별화"],
      "buy_reasons": ["차별성", "신뢰"],
      "compliance_notes": "오메가3 제품을 폄하하는 표현 금지. '충분하지 않다'가 아닌 '보완이 필요하다'는 뉘앙스 유지. 특정 경쟁사 브랜드명 절대 언급 금지. 성분 기능 설명은 식약처 인정 범위 내에서만."
    },
    {
      "brief_id": "vid_3",
      "format": "video",
      "duration_sec": 60,
      "outline_type": "F형",
      "appearance_type": "사람등장형",
      "narration": "여성VO_따뜻한",
      "concept_title": "처음엔 저도 안 믿었어요 - 엄마의 2주 일기",
      "angle": "사회증거형",
      "reframe_type": "문제재정의",
      "core_message": "반신반의로 시작한 뉴턴젤리를 2주간 먹인 엄마의 실제 변화 스토리를 통해, 비슷한 고민을 가진 부모가 '나도 시도해볼 수 있겠다'는 확신을 갖게 합니다.",
      "head": "엄마가 카메라를 보며 말하는 UGC 스타일. 자막+VO: '솔직히 말할게요. 처음엔 저도 안 믿었어요.' 핸드헬드 세로형, 집 거실 배경. (3초)",
      "body": "[Day 1] 엄마가 젤리를 꺼내 아이에게 주는 장면. 아이가 '이거 뭐야? 맛있다!' 반응. 자막: '샤인머스캣 맛이라 거부 없이 먹었어요.' (8초). [Day 3~5] 엄마 독백. '솔직히 3일째까지는 아무 변화 없었어요. 역시 그런 건가 싶었죠.' 아이가 여전히 산만한 일상 장면. (8초). [Day 7] 전환점. 엄마 표정이 밝아지며: '근데 일주일쯤 됐을 때 아이가 스스로 숙제를 끝낸 거예요. 처음이었어요.' 아이가 책상에서 공부하는 장면. (10초). [Day 14] 엄마가 감정이 복받치는 표정. '그리고 2주 후, 선생님한테 전화가 왔는데... 이번엔 달랐어요. 요즘 아이가 많이 차분해졌대요.' 눈시울이 붉어지는 엄마 클로즈업. (10초). [제품 설명] 뉴턴젤리 패키지 등장. 테아닌 150mg + 트립토판 150mg + 가바 성분 텍스트 오버레이. '200만 엄마들이 먼저 경험했습니다.' (8초)",
      "legs": "엄마가 카메라를 보며: '저처럼 고민만 하고 계시다면, 2주만 믿어보세요.' 자막: '효과 없으면 100% 환불. 뉴턴젤리.' CTA 버튼. (3초)",
      "narrative_arc": "도입(솔직한 고백으로 공감 형성) → 전개(시간 순서대로 변화를 보여주며 감정 곡선을 '의심 → 기대 → 감동'으로 설계) → 결말(선생님의 긍정 피드백이라는 사회적 증거 + 환불 보장으로 행동 유도)",
      "visual_direction": "전체적으로 UGC 리얼 후기 스타일. 핸드헬드 촬영감, 필터 없음, 집 거실·주방·아이방 배경. 자연광 위주. Day 1~5는 약간 어둡고 평범한 톤, Day 7부터 자연광이 더 밝아지며 톤 전환. Day 14 선생님 전화 장면에서 감정적 클라이맥스. 세로형(9:16) 릴스/숏폼 포맷.",
      "target_emotion": "공감",
      "key_copy_direction": "엄마의 실제 말투를 최대한 살린 내레이션. 광고처럼 들리지 않도록 자연스럽게. 감정의 흐름은 의심 → 실망 → 놀라움 → 감동 순서. 선생님의 피드백이 제3자 증거로 작동하게 배치. '저처럼 고민만 하고 계시다면'으로 직접 행동을 유도.",
      "keywords": ["2주 변화", "선생님 피드백", "UGC 후기", "200만개", "100% 환불"],
      "watch_reasons": ["몰입포맷", "의외성", "실용이익"],
      "buy_reasons": ["신뢰", "개선확신", "FOMO"],
      "compliance_notes": "후기는 개인 경험이며 효과에 개인차가 있음을 소자막으로 표기. ADHD 치료·진단 관련 표현 사용 금지. 선생님 전화 내용은 일반적 학교생활 피드백 수준으로 표현. '200만 엄마들'은 200만개 판매 기준이므로 정확한 표현은 '200만개 판매'로 소자막 보완."
    },
    {
      "brief_id": "vid_4",
      "format": "video",
      "duration_sec": 15,
      "outline_type": "H형",
      "appearance_type": "혼합형",
      "narration": "여성VO_전문적",
      "concept_title": "아이 예민함, 기질이 아니라 세로토닌입니다",
      "angle": "정보제공형",
      "reframe_type": "성분재정의",
      "core_message": "예민한 기질이라고 치부되는 아이의 과민 반응은 세로토닌 부족이 원인일 수 있으며, 트립토판이 세로토닌 생성의 필수 재료입니다.",
      "head": "아이가 작은 일에 감정 폭발하는 짧은 실사 컷(울거나 소리 지르는 장면, 1초). 즉시 모션그래픽 전환. 자막+VO: '예민한 기질? 사실 세로토닌이 부족한 겁니다.' (2초)",
      "body": "[씬1] 모션그래픽 인포그래픽. '세로토닌 = 감정 안정 호르몬. 부족하면 → 예민, 불안, 감정 폭발.' 뇌 일러스트에서 세로토닌 분자가 줄어드는 애니메이션. (4초). [씬2] '세로토닌의 재료 = 트립토판 (필수 아미노산, 체내 합성 불가).' 트립토판 → 세로토닌 변환 흐름도. 뉴턴젤리에 트립토판 150mg 함유 강조. (4초). [씬3] 실사 전환. 차분하게 놀고 있는 아이 + 제품 패키지 자연스러운 배치. (2초)",
      "legs": "자막+VO: '매일 젤리 하나로 세로토닌 재료 보충. 뉴턴젤리.' CTA: '성분 자세히 보기' (3초)",
      "narrative_arc": "도입(예민함을 기질이 아닌 세로토닌 문제로 재정의하는 반전 훅) → 전개(세로토닌 메커니즘과 트립토판의 역할을 15초 안에 압축 전달) → 결말(간결한 제품 연결 + 정보 탐색형 CTA)",
      "visual_direction": "도입 1초만 실사(아이 감정 폭발), 이후 딥그린 배경 모션그래픽으로 전환. 뇌 일러스트는 심플한 라인 드로잉 스타일. 세로토닌 분자는 옐로우(#FFF9C4), 트립토판은 오렌지(#FF7043) 강조. 마지막 씬만 실사로 복귀하며 따뜻한 자연광 톤. 정보 밀도 높지만 시각적으로 깔끔하게.",
      "target_emotion": "신뢰",
      "key_copy_direction": "전문적이지만 쉬운 언어. '세로토닌이 뭔지' 모르는 엄마도 15초 안에 이해할 수 있도록. 핵심은 '예민함 = 기질이 아닌 영양 문제'라는 재정의. VO는 차분하고 또박또박한 전문가 톤.",
      "keywords": ["세로토닌", "트립토판", "예민함", "감정 안정", "필수 아미노산"],
      "watch_reasons": ["실용이익", "시각차별화", "짧은메시지"],
      "buy_reasons": ["신뢰", "차별성"],
      "compliance_notes": "세로토닌 부족을 의학적 진단(우울증 등)과 연결짓지 않기. '감정 안정에 도움을 줄 수 있는 성분'으로 표현. 트립토판의 기능은 식품 영양학적 맥락에서만 설명. 일반식품이므로 건강기능식품 인증 마크 사용 금지."
    },
    {
      "brief_id": "vid_5",
      "format": "video",
      "duration_sec": 30,
      "outline_type": "B형",
      "appearance_type": "사람등장형",
      "narration": "아이목소리",
      "concept_title": "약 말고 젤리 - ADHD 회색지대 엄마를 위한 첫 선택",
      "angle": "감성소구",
      "reframe_type": "경쟁비교",
      "core_message": "ADHD 진단 전 회색지대에서 불안해하는 엄마에게, 약이 아닌 천연 성분 젤리로 먼저 시작할 수 있다는 안도감과 희망을 전합니다.",
      "head": "아이 목소리(VO): '엄마, 나 왜 자꾸 혼나?' 화면은 어두운 방에서 혼자 앉아있는 아이의 뒷모습 실루엣. (3초)",
      "body": "[씬1] 엄마 시점 몽타주. 소아과 대기실, 인터넷에서 'ADHD 증상' 검색하는 손, 한숨 쉬는 엄마 얼굴. 자막: '약을 먹여야 할까... 아직은 아닌 것 같은데.' (5초). [씬2] 화면 톤 전환(어둡고 차가운 톤 → 따뜻한 자연광). 엄마가 뉴턴젤리 스틱포를 열어 아이에게 건네는 장면. 아이 목소리(VO): '엄마, 이거 맛있다! 매일 먹어도 돼?' 아이가 웃으며 젤리를 먹는 장면. (5초). [씬3] 성분 텍스트 오버레이: '녹차 유래 테아닌 150mg + 세로토닌 재료 트립토판 150mg. 설탕·액상과당 무첨가. 약국 입점 제품.' 제품 패키지 클로즈업. (6초). [씬4] 아이가 밝은 표정으로 교실에서 손을 들고 있는 장면. 엄마 미소. 아이 목소리(VO): '엄마, 오늘 선생님이 칭찬해줬어!' (5초)",
      "legs": "자막: '약 전에 먼저 시도해보세요. 효과 없으면 100% 환불.' 제품 + 쿠폰팩 시각 + CTA 버튼. 아이 목소리(VO): '엄마, 고마워.' (3초)",
      "narrative_arc": "도입(아이의 순수한 질문으로 부모 감정 직격) → 전개(약에 대한 불안 → 천연 성분 젤리라는 대안 발견 → 아이의 긍정 반응으로 안도) → 결말(변화된 아이의 학교생활 + 감성적 CTA)",
      "visual_direction": "도입은 블루-그레이 톤의 어두운 실루엣으로 감정적 무게감. 중반부터 따뜻한 옐로우-그린 자연광으로 전환. 아이의 웃는 얼굴 클로즈업에 집중. 제품 장면은 밝은 화이트 배경에 그린 액센트. 마지막 교실 장면은 햇살이 비치는 창가. 전체적으로 어둠에서 빛으로의 감정 여정.",
      "target_emotion": "희망",
      "key_copy_direction": "아이 목소리 나레이션이 전체 감성을 이끔. '엄마, 나 왜 자꾸 혼나?'로 시작해 '엄마, 고마워'로 끝나는 감정의 완성. 성분 설명은 텍스트 오버레이로 시각 전달하여 감성 흐름을 깨지 않게 처리. 약 vs 자연 성분 대비는 직접적이지 않고 엄마의 내면 고민으로 간접 표현.",
      "keywords": ["ADHD 회색지대", "약 말고 젤리", "아이 목소리", "천연 성분", "100% 환불"],
      "watch_reasons": ["몰입포맷", "의외성", "시각차별화"],
      "buy_reasons": ["개선확신", "FOMO", "신뢰"],
      "compliance_notes": "ADHD 치료 대안이라는 표현 절대 금지. '약 전에 시도'는 의료 행위 대체가 아닌 영양 보충 차원으로 표현. 소아과 장면은 진단·처방 장면이 아닌 일반 대기실 수준으로만. 아이 목소리 사용 시 과도한 감정 조작으로 느껴지지 않도록 자연스러운 톤 유지. '100% 환불' 조건은 소자막 표기 필수."
    }
  ]
}
