{
  "brief_id": "vid_1",
  "campaign_id": "뉴턴젤리_20260329_203641",
  "product_name": "뉴턴젤리",
  "concept_title": "선생님 전화가 줄었어요",
  "duration_sec": 30,
  "format": "9:16 Reel/스토리",
  "outline_type": "A형",
  "appearance_type": "사람등장형",
  "narration": "여성VO_따뜻한",
  "hook": "오늘 또 선생님 전화 왔어요",
  "scenes": [
    {
      "scene_no": 1,
      "time_range": "0~3초",
      "label": "HEAD",
      "visual": "어두운 실내 조명의 주방 또는 거실. 30대 후반~40대 초반 엄마가 스마트폰 화면을 보며 무거운 표정으로 한숨을 내쉬는 클로즈업. 화면 속 알림: '담임선생님 부재중 1'. 엄마의 미간에 주름이 잡히는 표정.",
      "vo_or_caption": "VO(여성, 따뜻하지만 묵직하게): '오늘 또 선생님 전화 왔어요...'\n자막 오버레이(화면 하단 중앙, 흰색 고딕): '오늘 또 선생님 전화 왔어요...'",
      "direction": "핸드헬드 클로즈업으로 흔들림 없이 안정적으로 촬영. 엄마 손과 스마트폰 화면이 동시에 프레임에 잡히도록 45도 앵글. 조명은 자연광 차단 후 창문 틈 빛만 허용하여 무거운 분위기 연출. 배경 흐림 처리(보케).",
      "bgm_direction": "잔잔하고 약간 무거운 피아노 싱글 노트. 빠르기 Andante(70~80 BPM). 감정적 공백을 만드는 미니멀 사운드."
    },
    {
      "scene_no": 2,
      "time_range": "3~6초",
      "label": "BODY_1",
      "visual": "학교 교실 장면. 수업 중 자리를 이탈해 교실을 돌아다니는 초등학생 아이의 뒷모습 짧은 컷. 선생님이 곤란한 표정으로 바라보는 장면. 창문 외부의 밝은 빛과 교실 내부의 형광등 조명 대비.",
      "vo_or_caption": "VO: '우리 아이 산만한 게 의지 문제일까요?'\n자막 오버레이(화면 중앙, 흰색): '우리 아이 산만한 게 의지 문제일까요?'",
      "direction": "빠른 컷 전환(1~1.5초 컷). 아이 얼굴은 블러 처리하여 특정인 연상 방지. 교사와 학교를 특정할 수 있는 요소(교명 현판, 교사 얼굴 등) 모두 제거. 핸드헬드 카메라로 현장감 있게.",
      "bgm_direction": "긴장감을 약간 높이는 스트링 추가. 이전 씬에서 자연스럽게 전환."
    },
    {
      "scene_no": 3,
      "time_range": "6~14초",
      "label": "BODY_2",
      "visual": "딥그린(#397900) 배경의 모션그래픽 화면. 뇌 실루엣 일러스트 중앙 배치. 왼쪽부터 '스트레스 → 코르티솔 과다 → 신경전달물질 불균형' 3단계 플로우 차트가 오렌지(#FF7043) 화살표로 순차 등장. 마지막에 '산만함 · 예민함 · 집중력 저하' 텍스트 팝업. 화면 하단에 '이 악순환이 원인입니다' 강조 텍스트.",
      "vo_or_caption": "VO: '산만한 건 의지 문제가 아닐 수 있어요. 스트레스가 쌓이면 신경전달물질 불균형이 생기고, 이 악순환이 산만함을 만들어냅니다.'\n자막 오버레이(순차 등장):\n- '스트레스 → 코르티솔 과다'\n- '신경전달물질 불균형'\n- '산만함 · 예민함 · 집중력 저하'\n- '이 악순환이 원인입니다' (오렌지 #FF7043 강조)",
      "direction": "텍스트와 아이콘이 왼쪽에서 오른쪽으로 슬라이드인. 각 요소 0.3초 간격 순차 등장. 뇌 일러스트는 라인 드로잉 스타일. '악순환'이라는 단어에 오렌지 강조 처리. 화면 전체 딥그린 배경, 텍스트는 화이트, 강조 키워드만 오렌지.",
      "bgm_direction": "정보 전달 구간. BGM을 낮추고 VO가 명확히 들리도록 조정. 잔잔한 배경음으로 유지."
    },
    {
      "scene_no": 4,
      "time_range": "14~19초",
      "label": "BODY_3",
      "visual": "딥그린 배경에서 뉴턴젤리 패키지 등장. 세 가지 성분 텍스트가 아이콘과 함께 하나씩 팝업: '테아닌 150mg — 심리적 안정', '트립토판 150mg — 세로토닌 생성 재료', '가바(GABA) — 신경 안정'. 마지막에 뉴턴젤리 단상자 패키지 클로즈업 (brand/images/뉴턴젤리/단상자누끼_편집.png 사용).",
      "vo_or_caption": "VO: '테아닌 150mg, 트립토판 150mg, 가바. 이 세 가지가 악순환의 고리를 끊어주도록 설계된 게 뉴턴젤리입니다.'\n자막 오버레이:\n- '테아닌 150mg' (아이콘 + 텍스트)\n- '트립토판 150mg' (아이콘 + 텍스트)\n- '가바(GABA)' (아이콘 + 텍스트)\n- '악순환의 고리를 끊어주는 성분' (화면 하단 강조)",
      "direction": "각 성분 텍스트는 바운스 인 애니메이션으로 등장. 제품 패키지는 부드럽게 줌인하며 등장. 성분명은 오렌지(#FF7043), 설명 텍스트는 화이트(#FFFFFF). 배경은 딥그린에서 점점 밝아지는 그라데이션 처리 시작.",
      "bgm_direction": "희망적 분위기로 전환. 업비트 없이 밝고 따뜻한 피아노 코드로 부드럽게 전환."
    },
    {
      "scene_no": 5,
      "time_range": "19~27초",
      "label": "BODY_4",
      "visual": "자연광이 가득한 밝은 거실. 같은 아이가 책상에 차분하게 앉아 숙제를 하는 뒷모습. 엄마가 뒤에서 따뜻한 미소를 지으며 바라보는 라이프스타일 컷. 햇살이 창문을 통해 비치며 따뜻하고 희망적인 분위기. 엄마의 표정이 씬 1과 대조적으로 환하게 밝아진 상태.",
      "vo_or_caption": "VO: '아이가 차분해지는 걸 느끼는 순간, 엄마도 달라집니다.'\n자막 오버레이(화면 하단): '아이가 차분해지는 순간, 엄마도 달라집니다'",
      "direction": "부드러운 카메라 줌인으로 엄마 미소 클로즈업. 자연광 최대 활용. 따뜻한 옐로우-그린 컬러 그레이딩 적용. 씬 1(어두운 주방)과 씬 5(밝은 거실)의 감정 대비가 시각적으로 명확하게 느껴지도록 조명 차이를 극대화.",
      "bgm_direction": "BGM이 희망적으로 절정에 이름. 따뜻한 현악기 또는 기타 아르페지오 가미."
    },
    {
      "scene_no": 6,
      "time_range": "27~30초",
      "label": "LEGS",
      "visual": "밝은 화이트 배경에 뉴턴젤리 단상자 패키지 정면 배치. '100% 환불 보장' 배지(원형, 딥그린 배경+화이트 텍스트)가 우측 상단에 팝업. CTA 버튼 '지금 시작하기' (오렌지 #FF7043 배경). 화면 최하단에 소자막으로 면책 문구.",
      "vo_or_caption": "VO: '14일 안에 변화 없으면 전액 환불. 뉴턴젤리, 지금 시작하세요.'\n자막 오버레이:\n- '14일 변화 없으면 전액 환불' (굵은 고딕, 딥그린)\n- '지금 시작하기' (CTA 버튼)\n소자막(최하단, 8pt 이하): '100% 환불은 주문일로부터 14일 이내, 10포 이하 섭취 시 적용됩니다. 이 제품은 질병의 예방 및 치료를 위한 의약품이 아닙니다.'",
      "direction": "패키지 등장은 아래에서 위로 슬라이드인. 배지는 팝업 바운스 효과. CTA 버튼은 살짝 반짝이는 애니메이션으로 클릭을 유도. 마지막 프레임에 3자 이상 읽기 충분한 시간 동안 정지.",
      "bgm_direction": "BGM 페이드아웃. 마지막 2초는 무음 또는 아주 낮은 볼륨 유지."
    }
  ],
  "vo_full_transcript": "오늘 또 선생님 전화 왔어요... / 우리 아이 산만한 게 의지 문제일까요? / 산만한 건 의지 문제가 아닐 수 있어요. 스트레스가 쌓이면 신경전달물질 불균형이 생기고, 이 악순환이 산만함을 만들어냅니다. / 테아닌 150mg, 트립토판 150mg, 가바. 이 세 가지가 악순환의 고리를 끊어주도록 설계된 게 뉴턴젤리입니다. / 아이가 차분해지는 걸 느끼는 순간, 엄마도 달라집니다. / 14일 안에 변화 없으면 전액 환불. 뉴턴젤리, 지금 시작하세요.",
  "total_character_count": 167,
  "disclaimer_placement": "마지막 씬 하단 소자막 (8pt 이하, 화면 최하단 중앙 정렬, 화이트 또는 라이트그레이 텍스트)",
  "disclaimer_text": "100% 환불은 주문일로부터 14일 이내, 10포 이하 섭취 시 적용됩니다. 이 제품은 질병의 예방 및 치료를 위한 의약품이 아닙니다. 개인에 따라 결과가 다를 수 있습니다.",
  "compliance_self_check": {
    "approved_claims_only": true,
    "no_prohibited_terms": true,
    "disclaimer_included": true,
    "adhd_treatment_claim_absent": true,
    "no_competitor_brand_name": true,
    "refund_condition_disclosed": true,
    "school_scene_generalized": true
  },
  "overall_tone": "무거운 공감에서 희망으로. 엄마의 실제 일상 언어로 시작해 과학적 근거로 전환하는 신뢰감 있는 구조. VO는 친구 엄마가 조언해주는 듯 따뜻하고 자연스러운 톤.",
  "production_notes": "씬 1과 씬 5의 조명 대비가 감정 곡선의 핵심입니다. 씬 1은 창문 빛 최소화, 씬 5는 자연광 최대 활용. 아이 얼굴은 전체 영상에서 블러 또는 뒷모습 처리 필수. 학교 장면(씬 2)에서 교명·교사 얼굴 등 특정 학교 연상 요소 완전 제거. 모션그래픽 씬(씬 3~4)은 딥그린 배경에 화이트 텍스트, 강조어만 오렌지 적용. 제품 패키지는 brand/images/뉴턴젤리/단상자누끼_편집.png 사용. 전체 VO 읽기 속도: 분당 280자 기준 약 30초 적합."
}
